instagram_profile_downloader/__init__.py
instagram_profile_downloader/instagram_profile_downloader.py
instagram_profile_downloader/private.py
instagram_profile_downloader-1.1.7.dist-info/LICENSE
instagram_profile_downloader-1.1.7.dist-info/METADATA
instagram_profile_downloader-1.1.7.dist-info/WHEEL
instagram_profile_downloader-1.1.7.dist-info/entry_points.txt
instagram_profile_downloader-1.1.7.dist-info/top_level.txt
instagram_profile_downloader-1.1.7.dist-info/RECORD
