Metadata-Version: 2.1
Name: instagram-profile-downloader
Version: 1.1.7
Summary: A tool to download all images and videos and story highlights from an Instagram profile.
Home-page: https://github.com/tadeasf/instagram_profile_downloader
Author: Tadeas Fort
Author-email: taddy.fort@gmail.com
Classifier: Programming Language :: Python :: 3
Classifier: License :: OSI Approved :: MIT License
Classifier: Operating System :: OS Independent
Requires-Python: >=3.11
License-File: LICENSE
Requires-Dist: click
Requires-Dist: rich-click
Requires-Dist: opencv-python
Requires-Dist: pillow
Requires-Dist: loguru
Requires-Dist: requests
Requires-Dist: instaloader
Requires-Dist: asyncio
Requires-Dist: aiohttp
Requires-Dist: setuptools
